Metadata-Version: 2.1
Name: genairics
Version: 0.2.2
Summary: GENeric AIRtight omICS pipelines
Home-page: https://github.com/beukueb/genairics
Author: Christophe Van Neste
Author-email: christophe.vanneste@ugent.be
License: GNU GENERAL PUBLIC LICENSE
Platform: UNKNOWN
Provides-Extra: interactive_console
Provides-Extra: simulation
Provides-Extra: ChIPseq
Provides-Extra: wui
